framefox/__init__.py
framefox/application.py
framefox/cli.py
framefox/core/kernel.py
framefox/core/bundle/abstract_bundle.py
framefox/core/bundle/bundle_manager.py
framefox/core/config/settings.py
framefox/core/controller/abstract_controller.py
framefox/core/controller/controller_resolver.py
framefox/core/debug/exception/auth_exception.py
framefox/core/debug/exception/base_exception.py
framefox/core/debug/exception/controller_exception.py
framefox/core/debug/exception/database_exception.py
framefox/core/debug/exception/di_exception.py
framefox/core/debug/exception/file_exception.py
framefox/core/debug/exception/http_exception.py
framefox/core/debug/exception/service_exception.py
framefox/core/debug/exception/settings_exception.py
framefox/core/debug/exception/template_exception.py
framefox/core/debug/exception/validation_exception.py
framefox/core/debug/handler/startup_error_handler.py
framefox/core/debug/profiler/profiler.py
framefox/core/debug/profiler/profiler_controller.py
framefox/core/debug/profiler/collector/data_collector.py
framefox/core/debug/profiler/collector/exception_data_collector.py
framefox/core/debug/profiler/collector/log_data_collector.py
framefox/core/debug/profiler/collector/memory_data_collector.py
framefox/core/debug/profiler/collector/request_data_collector.py
framefox/core/debug/profiler/collector/route_data_collector.py
framefox/core/debug/profiler/collector/sentry_data_collector.py
framefox/core/debug/profiler/collector/sql_data_collector.py
framefox/core/debug/profiler/collector/sql_interceptor.py
framefox/core/debug/profiler/collector/time_data_collector.py
framefox/core/debug/profiler/collector/user_data_collector.py
framefox/core/debug/sentry/sentry_manager.py
framefox/core/di/__init__.py
framefox/core/di/service_cache_manager.py
framefox/core/di/service_config.py
framefox/core/di/service_container.py
framefox/core/di/service_definition.py
framefox/core/di/service_factory_manager.py
framefox/core/di/service_registry.py
framefox-1.1.3.dist-info/licenses/LICENSE
framefox-1.1.3.dist-info/METADATA
framefox-1.1.3.dist-info/WHEEL
framefox-1.1.3.dist-info/entry_points.txt
framefox-1.1.3.dist-info/top_level.txt
framefox-1.1.3.dist-info/RECORD
